litegpt/AsyncLiteGPT.py
litegpt/LiteGPT.py
litegpt/__init__.py
litegpt/lib/AsyncHistory.py
litegpt/lib/History.py
litegpt/lib/__init__.py
litegpt/lib/exceptions.py
litegpt/lib/utils/Dtime.py
litegpt/lib/utils/__init__.py
litegpt-1.3.3.dist-info/METADATA
litegpt-1.3.3.dist-info/WHEEL
litegpt-1.3.3.dist-info/top_level.txt
litegpt-1.3.3.dist-info/RECORD
