Metadata-Version: 2.1
Name: litegpt
Version: 1.3.3
Summary: LiteGPT provides free access to the ChatGPT and image generator
Home-page: https://github.com/RedPiarOfficial/LiteGPT
Author: RedPiar
Author-email: Redpiar.official@gmail.com
License: MIT
Project-URL: Source, https://github.com/RedPiarOfficial/LiteGPT
Keywords: artificial-intelligence,ai,lite,gpt,assistant,chatbot,image-generator
Classifier: Programming Language :: Python :: 3
Classifier: License :: OSI Approved :: MIT License
Classifier: Operating System :: OS Independent
Requires-Python: >=3.8
Requires-Dist: httpx
Requires-Dist: httpx[http2]
Requires-Dist: aiofiles
